antakia/__init__.py
antakia/antakia.py
antakia/assets/examples/california_housing.csv
antakia/assets/examples/car_prices.csv
antakia/assets/examples/climate_change_survey-X_test.csv
antakia/assets/examples/climate_change_survey-X_train.csv
antakia/assets/examples/climate_change_survey-y_test.csv
antakia/assets/examples/climate_change_survey-y_train.csv
antakia/assets/examples/march_madness.csv
antakia/assets/examples/titanic-train.csv
antakia/assets/examples/wages.csv
antakia/assets/logo_ai-vidence.png
antakia/assets/logo_antakia.png
antakia/assets/logo_antakia_horizontal.png
antakia/config.py
antakia/gui/__init__.py
antakia/gui/app_bar/__init__.py
antakia/gui/app_bar/color_switch.py
antakia/gui/app_bar/dimension_switch.py
antakia/gui/app_bar/explanation_values.py
antakia/gui/app_bar/top_bar.py
antakia/gui/graphical_elements/__init__.py
antakia/gui/graphical_elements/color_table.py
antakia/gui/graphical_elements/rule_slider.py
antakia/gui/graphical_elements/sub_model_table.py
antakia/gui/gui.py
antakia/gui/helpers/__init__.py
antakia/gui/helpers/data.py
antakia/gui/helpers/metadata.py
antakia/gui/helpers/progress_bar.py
antakia/gui/high_dim_exp/__init__.py
antakia/gui/high_dim_exp/figure_display.py
antakia/gui/high_dim_exp/highdimexplorer.py
antakia/gui/high_dim_exp/projected_value_bank.py
antakia/gui/high_dim_exp/projected_values_selector.py
antakia/gui/splash_screen.py
antakia/gui/tabs/__init__.py
antakia/gui/tabs/model_explorer.py
antakia/gui/tabs/rule_wgt.py
antakia/gui/tabs/ruleswidget.py
antakia/gui/tabs/tab1.py
antakia/gui/tabs/tab2.py
antakia/gui/tabs/tab3.py
antakia/gui/widget_utils.py
antakia/utils/__init__.py
antakia/utils/checks.py
antakia/utils/colors.py
antakia/utils/dummy_datasets.py
antakia/utils/examples.py
antakia/utils/logging_utils.py
antakia/utils/other_utils.py
antakia/utils/stats.py
antakia-0.4.6.dist-info/LICENSE
antakia-0.4.6.dist-info/METADATA
antakia-0.4.6.dist-info/WHEEL
antakia-0.4.6.dist-info/RECORD
