Metadata-Version: 2.1
Name: antakia
Version: 0.4.6
Summary: AI made Xplainable
Keywords: XAI,explainability,AI,ML,machine learning,artificial intelligence
Author: Pierre HULOT
Author-email: pierre@ai-vidence.com
Requires-Python: >=3.10,<3.12
Classifier: Operating System :: OS Independent
Classifier: Programming Language :: Python :: 3
Classifier: Programming Language :: Python :: 3.10
Classifier: Programming Language :: Python :: 3.11
Requires-Dist: antakia-ac (>=0.2.14,<0.3.0)
Requires-Dist: antakia-core (==0.4.6)
Requires-Dist: ipyvuetify (<1.9.0)
Requires-Dist: ipywidgets (>=7.6)
Requires-Dist: jupyterlab (>=3)
Requires-Dist: pdpbox (>=0.3.0,<0.4.0)
Requires-Dist: plotly (<=5.19.0)
Requires-Dist: python-dotenv (>=1.0.0,<2.0.0)
Requires-Dist: requests (>=2.31.0,<3.0.0)
